intel_toolkit/__init__.py
intel_toolkit/cisa_kev.py
intel_toolkit/cli.py
intel_toolkit/cve_prioritizer.py
intel_toolkit/cveshield.py
intel_toolkit/inthewild.py
intel_toolkit/iris_api.py
intel_toolkit/nuclei_templates.py
intel_toolkit/sploitus.py
intel_toolkit/strobes_vi.py
intel_toolkit-0.1.19.dist-info/LICENSE
intel_toolkit-0.1.19.dist-info/METADATA
intel_toolkit-0.1.19.dist-info/WHEEL
intel_toolkit-0.1.19.dist-info/entry_points.txt
intel_toolkit-0.1.19.dist-info/RECORD
