Metadata-Version: 2.1
Name: intel-toolkit
Version: 0.1.19
Summary: Toolkit with methods to consume vulnerability risk mapping APIs
License: BSD-3-Clause
Author: cristianovisk
Author-email: cristianovisk@gmail.com
Requires-Python: >=3.10,<4.0
Classifier: Development Status :: 5 - Production/Stable
Classifier: Intended Audience :: Developers
Classifier: License :: OSI Approved :: BSD License
Classifier: Programming Language :: Python :: 3
Classifier: Programming Language :: Python :: 3.10
Classifier: Programming Language :: Python :: 3.11
Classifier: Programming Language :: Python :: 3.9
Requires-Dist: brotli (>=1.0.9,<2.0.0)
Requires-Dist: httpx[http2] (>=0.24.1,<0.25.0)
Requires-Dist: openpyxl (>=3.1.2,<4.0.0)
Requires-Dist: pandas (>=2.0.3,<3.0.0)
Requires-Dist: pyshorteners (>=1.0.1,<2.0.0)
Requires-Dist: requests (>=2.31.0,<3.0.0)
Requires-Dist: rich (>=13.5.2,<14.0.0)
Requires-Dist: streamlit (>=1.28.1,<2.0.0)
Project-URL: Bug Tracker, https://github.com/cristianovisk/intel-toolkit/issues
Project-URL: Código, https://github.com/cristianovisk/intel-toolkit
Project-URL: Documentação, https://github.com/cristianovisk/intel-toolkit/blob/main/README.md
